neuquet/__init__.py
neuquet/server.py
neuquet/public_html/asset-manifest.json
neuquet/public_html/favicon.ico
neuquet/public_html/index.html
neuquet/public_html/logo192.png
neuquet/public_html/logo512.png
neuquet/public_html/manifest.json
neuquet/public_html/robots.txt
neuquet/public_html/static/css/main.463b17d0.css
neuquet/public_html/static/css/main.463b17d0.css.map
neuquet/public_html/static/js/787.d7375a20.chunk.js
neuquet/public_html/static/js/787.d7375a20.chunk.js.map
neuquet/public_html/static/js/main.8e40891e.js
neuquet/public_html/static/js/main.8e40891e.js.LICENSE.txt
neuquet/public_html/static/js/main.8e40891e.js.map
neuquet_foolean-0.0.1.dist-info/LICENSE
neuquet_foolean-0.0.1.dist-info/METADATA
neuquet_foolean-0.0.1.dist-info/WHEEL
neuquet_foolean-0.0.1.dist-info/top_level.txt
neuquet_foolean-0.0.1.dist-info/RECORD
