Metadata-Version: 2.1
Name: neuquet_foolean
Version: 0.0.1
Summary: A data analysis tool
Author-email: Sebastin Santy <neuquet.app@gmail.com>, Naved Rizvi <neuquet.app@gmail.com>
Project-URL: Homepage, https://github.com/SebastinSanty/neuquet
Project-URL: Issues, https://github.com/SebastinSanty/neuquet/issues
Classifier: Programming Language :: Python :: 3
Classifier: License :: OSI Approved :: MIT License
Classifier: Operating System :: OS Independent
Requires-Python: >=3.8
License-File: LICENSE
